{
    "id": "31814",
    "name": "元宇宙PicoNeo3开发初探",
    "lecturer": "高校学生与虚拟现实、游戏开发企业一线研发人员。    ",
    "descriptionText": "掌握PicoNeo3一体机在虚拟现实与游戏领域的开发重点与难点，对商业开发的进度与质量保障起到事半功",
    "chapters": [
        {
            "id": "106185",
            "name": "PicoNeo3环境配置",
            "courseId": "31814",
            "sections": [
                {
                    "id": "844837",
                    "name": "PicoNeo3开发初探宣传片",
                    "courseId": "31814",
                    "url": "/31814/0_0_844837_HD.m3u8",
                    "urls": [
                        {
                            "width": 540,
                            "height": 540,
                            "definition": "LD",
                            "url": "/31814/0_0_844837_LD.m3u8",
                            "format": "m3u8",
                            "desc": "标清",
                            "encryptionType": 1,
                            "plaintext": "PsiQHlO6kGytTNgZNo+/PtAmRjV/e66Kt+LLEQJibqA=",
                            "rand": "/Q661KcJw81STNWNKNEVmmaUHaCpUqIlrKQiWLkZKkM=",
                            "encrypt": 1,
                            "duration": "84.1264",
                            "rate": "369.535",
                            "randInit": "EizGAndHe9aXMeSj"
                        },
                        {
                            "width": 720,
                            "height": 720,
                            "definition": "SD",
                            "url": "/31814/0_0_844837_SD.m3u8",
                            "format": "m3u8",
                            "desc": "高清",
                            "encryptionType": 1,
                            "plaintext": "xbLbE8G7ORlD2fdhpn0n+PAKbmv2wlZy+1Jx+rNwNMM=",
                            "rand": "ZO/aYlo2gVM5BuRHn7sw2LSV/rnDEj9I2DYOHHOFz60=",
                            "encrypt": 1,
                            "duration": "84.1264",
                            "rate": "557.735",
                            "randInit": "EizGAndHe9aXMeSj"
                        },
                        {
                            "width": 1080,
                            "height": 1080,
                            "definition": "HD",
                            "url": "/31814/0_0_844837_HD.m3u8",
                            "format": "m3u8",
                            "desc": "超清",
                            "encryptionType": 1,
                            "plaintext": "ELnqnuF+GI1sDosDWZ1m9KHT7hMGvzQxpZVP5AWlLDA=",
                            "rand": "vxqU9+6XshUMyT6qucc5zpyurgMT64cJW1Q7HnaWwUs=",
                            "encrypt": 1,
                            "duration": "84.1489",
                            "rate": "750.919",
                            "randInit": "EizGAndHe9aXMeSj"
                        }
                    ]
                },
                {
                    "id": "844836",
                    "name": "PicoNeo3开箱评测",
                    "courseId": "31814",
                    "url": "/31814/0_1_844836_HD.m3u8",
                    "urls": [
                        {
                            "width": 540,
                            "height": 540,
                            "definition": "LD",
                            "url": "/31814/0_1_844836_LD.m3u8",
                            "format": "m3u8",
                            "desc": "标清",
                            "encryptionType": 1,
                            "plaintext": "VflfJw0rkVti5Ssx7yBmhCV4taxtdQ9SvhZjd9g5CUg=",
                            "rand": "FVKNJtAELrguoSDrV9oRUPCU9YCEnONfPp2VOya+0FY=",
                            "encrypt": 1,
                            "duration": "402.6064",
                            "rate": "452.952",
                            "randInit": "rACnbABGmWFTaGns"
                        },
                        {
                            "width": 720,
                            "height": 720,
                            "definition": "SD",
                            "url": "/31814/0_1_844836_SD.m3u8",
                            "format": "m3u8",
                            "desc": "高清",
                            "encryptionType": 1,
                            "plaintext": "PQM+706kKkKl36pZHjcMIRfxlfEOZW9sEdkiyFC8d9s=",
                            "rand": "czkIxR0f+ayh2lCfJHQ+3Spv2CFZqnrsRVOcrcn+chs=",
                            "encrypt": 1,
                            "duration": "402.6064",
                            "rate": "701.941",
                            "randInit": "rACnbABGmWFTaGns"
                        },
                        {
                            "width": 1080,
                            "height": 1080,
                            "definition": "HD",
                            "url": "/31814/0_1_844836_HD.m3u8",
                            "format": "m3u8",
                            "desc": "超清",
                            "encryptionType": 1,
                            "plaintext": "U5TXq9qX34uD8xXW7BZ1AoiSYUfbm6iWmdX+3fOunQ0=",
                            "rand": "v9cvs+kvq32bDcSXkNjqSRVGA6khLu6dxyrnKJcLhrA=",
                            "encrypt": 1,
                            "duration": "402.6064",
                            "rate": "949.309",
                            "randInit": "rACnbABGmWFTaGns"
                        }
                    ]
                },
                {
                    "id": "844835",
                    "name": "课程概述",
                    "courseId": "31814",
                    "url": "/31814/0_2_844835_HD.m3u8",
                    "urls": [
                        {
                            "width": 540,
                            "height": 540,
                            "definition": "LD",
                            "url": "/31814/0_2_844835_LD.m3u8",
                            "format": "m3u8",
                            "desc": "标清",
                            "encryptionType": 1,
                            "plaintext": "wpMG1RIz7ved2YjJ88pQFmqitjyC5qLohM4LAmZzF5Y=",
                            "rand": "CORgCdFT+/1SMtA4TkgUrubpVjDfQLBHbatyqFIduWE=",
                            "encrypt": 1,
                            "duration": "906.8464",
                            "rate": "368.51",
                            "randInit": "5mRWEz8J3A9nYzF3"
                        },
                        {
                            "width": 720,
                            "height": 720,
                            "definition": "SD",
                            "url": "/31814/0_2_844835_SD.m3u8",
                            "format": "m3u8",
                            "desc": "高清",
                            "encryptionType": 1,
                            "plaintext": "4WwH72ZfW2NVJgDPwp9FQWdTvkOQ07bUMlp7keWXGcw=",
                            "rand": "twGXr1zB7pGxqfNjrK58LvsUsvmzoXyeLG9GrhAG+NQ=",
                            "encrypt": 1,
                            "duration": "906.8464",
                            "rate": "560.068",
                            "randInit": "5mRWEz8J3A9nYzF3"
                        },
                        {
                            "width": 1080,
                            "height": 1080,
                            "definition": "HD",
                            "url": "/31814/0_2_844835_HD.m3u8",
                            "format": "m3u8",
                            "desc": "超清",
                            "encryptionType": 1,
                            "plaintext": "2ZLm5ZOuqeTYOLPIonXqXCQkGhzeSw5mCoKDCUdYtt0=",
                            "rand": "c/WoTSUQrasbshorzgiAV0rNlpGtHRrVwGe71sqgWxc=",
                            "encrypt": 1,
                            "duration": "906.8464",
                            "rate": "696.159",
                            "randInit": "5mRWEz8J3A9nYzF3"
                        }
                    ]
                },
                {
                    "id": "844834",
                    "name": "安装Unity与Android组件",
                    "courseId": "31814",
                    "url": "/31814/0_3_844834_HD.m3u8",
                    "urls": [
                        {
                            "width": 540,
                            "height": 540,
                            "definition": "LD",
                            "url": "/31814/0_3_844834_LD.m3u8",
                            "format": "m3u8",
                            "desc": "标清",
                            "encryptionType": 1,
                            "plaintext": "4qOprkgl3CKUaSuX5xU/KpxQyt06bMqbkNpJbIwAWdk=",
                            "rand": "0froRju6vbUlZ774pljdFnAvAwVOv0kVHrrH8NvRrDA=",
                            "encrypt": 1,
                            "duration": "982.9265",
                            "rate": "315.627",
                            "randInit": "E2372xPG2057DemK"
                        },
                        {
                            "width": 720,
                            "height": 720,
                            "definition": "SD",
                            "url": "/31814/0_3_844834_SD.m3u8",
                            "format": "m3u8",
                            "desc": "高清",
                            "encryptionType": 1,
                            "plaintext": "jgZY8ysn5CDAk9GglQqTMhwUJxB8hClH1BxxdsS/I9g=",
                            "rand": "rnRr63ehAijqO3mNWT3xoaWK/2mORXjI8ZriZS25Y8Q=",
                            "encrypt": 1,
                            "duration": "982.9265",
                            "rate": "464.865",
                            "randInit": "E2372xPG2057DemK"
                        },
                        {
                            "width": 1080,
                            "height": 1080,
                            "definition": "HD",
                            "url": "/31814/0_3_844834_HD.m3u8",
                            "format": "m3u8",
                            "desc": "超清",
                            "encryptionType": 1,
                            "plaintext": "B9Kyb0CvrabVfKQ6hmnOJWnbUFe4DNVucJRmLx5pED4=",
                            "rand": "isCLpV9rJU7EkctAIDhCgkGapQokIRw8imN1/wSbFNM=",
                            "encrypt": 1,
                            "duration": "982.9265",
                            "rate": "504.748",
                            "randInit": "E2372xPG2057DemK"
                        }
                    ]
                },
                {
                    "id": "844833",
                    "name": "下载安装PicoSDK",
                    "courseId": "31814",
                    "url": "/31814/0_4_844833_HD.m3u8",
                    "urls": [
                        {
                            "width": 540,
                            "height": 540,
                            "definition": "LD",
                            "url": "/31814/0_4_844833_LD.m3u8",
                            "format": "m3u8",
                            "desc": "标清",
                            "encryptionType": 1,
                            "plaintext": "TyhuBCmuN2A/RE2DAG5+9a4fjn4E1jPbNFqJxZ/7OSA=",
                            "rand": "FMZ21V7y/z/99k0w0Y8cZmbWm7SP7QLqwsJobZBOIdQ=",
                            "encrypt": 1,
                            "duration": "1014.9265",
                            "rate": "358.093",
                            "randInit": "NbyhmSKcwjwaNZ87"
                        },
                        {
                            "width": 720,
                            "height": 720,
                            "definition": "SD",
                            "url": "/31814/0_4_844833_SD.m3u8",
                            "format": "m3u8",
                            "desc": "高清",
                            "encryptionType": 1,
                            "plaintext": "mJk/Ros6hEnlC3FRGzj7wH2sUy2bnAhppKBVXciMUNA=",
                            "rand": "KVo/0vnj5BdQJMg0v9qr5bN9ZrHSlncVgfNu0sENWs4=",
                            "encrypt": 1,
                            "duration": "1014.9265",
                            "rate": "541.341",
                            "randInit": "NbyhmSKcwjwaNZ87"
                        },
                        {
                            "width": 1080,
                            "height": 1080,
                            "definition": "HD",
                            "url": "/31814/0_4_844833_HD.m3u8",
                            "format": "m3u8",
                            "desc": "超清",
                            "encryptionType": 1,
                            "plaintext": "5IvuO1TQ5vcJ75ezoHtszNxAkUwFR4IS21SdkeFtlC8=",
                            "rand": "HbsK4gIUteaWThzDrIiA/s0SQN/TqhVNFLiEPGSla2g=",
                            "encrypt": 1,
                            "duration": "1014.9265",
                            "rate": "645.474",
                            "randInit": "NbyhmSKcwjwaNZ87"
                        }
                    ]
                },
                {
                    "id": "844832",
                    "name": "Unity环境配置",
                    "courseId": "31814",
                    "url": "/31814/0_5_844832_HD.m3u8",
                    "urls": [
                        {
                            "width": 540,
                            "height": 540,
                            "definition": "LD",
                            "url": "/31814/0_5_844832_LD.m3u8",
                            "format": "m3u8",
                            "desc": "标清",
                            "encryptionType": 1,
                            "plaintext": "OxJ9PZIh/nl4VUn/RD2Bv6pS3vx2yEcdLTpq850aGZU=",
                            "rand": "r+H/r/Y68J1J6PIsMERjoEArJY8hsJA6exEPh3Brx+Y=",
                            "encrypt": 1,
                            "duration": "963.4465",
                            "rate": "359.116",
                            "randInit": "JdQPbY4ApkbriMX8"
                        },
                        {
                            "width": 720,
                            "height": 720,
                            "definition": "SD",
                            "url": "/31814/0_5_844832_SD.m3u8",
                            "format": "m3u8",
                            "desc": "高清",
                            "encryptionType": 1,
                            "plaintext": "Zh46JWEmxBfC9O2JoY/n6NGMxXEZqHlnCRWmDaiBQ84=",
                            "rand": "u3Miu2s2LTXvHLR5FPgXKtXog284OlmLD2VOWdF/hJk=",
                            "encrypt": 1,
                            "duration": "963.4465",
                            "rate": "534.754",
                            "randInit": "JdQPbY4ApkbriMX8"
                        },
                        {
                            "width": 1080,
                            "height": 1080,
                            "definition": "HD",
                            "url": "/31814/0_5_844832_HD.m3u8",
                            "format": "m3u8",
                            "desc": "超清",
                            "encryptionType": 1,
                            "plaintext": "YreCPObvFHOxYNDrW6u41ubtXWHmtvF5QF82IZyBlPU=",
                            "rand": "J8Fk8tNzGDCmD7qabMb5U1jk6JTlU3ADxawaZk0LQL0=",
                            "encrypt": 1,
                            "duration": "963.4465",
                            "rate": "598.155",
                            "randInit": "JdQPbY4ApkbriMX8"
                        }
                    ]
                },
                {
                    "id": "844831",
                    "name": "建立项目XR环境(上)",
                    "courseId": "31814",
                    "url": "/31814/0_6_844831_HD.m3u8",
                    "urls": [
                        {
                            "width": 540,
                            "height": 540,
                            "definition": "LD",
                            "url": "/31814/0_6_844831_LD.m3u8",
                            "format": "m3u8",
                            "desc": "标清",
                            "encryptionType": 1,
                            "plaintext": "El3DNcz+rQcYuyliHld75fMpmAMTfX/CA9cC0oEEO0k=",
                            "rand": "clzH+2JBsmWQ7VruZhlBiPMJF+z8MBI5kkJPoeQ9GME=",
                            "encrypt": 1,
                            "duration": "1028.8464",
                            "rate": "381.456",
                            "randInit": "tF2nB3CHWHJjNGaN"
                        },
                        {
                            "width": 720,
                            "height": 720,
                            "definition": "SD",
                            "url": "/31814/0_6_844831_SD.m3u8",
                            "format": "m3u8",
                            "desc": "高清",
                            "encryptionType": 1,
                            "plaintext": "Q4D+rmMjKzG1ZlZsLU2kzNG2lhnXD+nriLmIxIhAKGo=",
                            "rand": "qUXdBnbew7RgY2ipofI8rJGLz2cpb++x5jLQDnESYU8=",
                            "encrypt": 1,
                            "duration": "1028.8464",
                            "rate": "562.017",
                            "randInit": "tF2nB3CHWHJjNGaN"
                        },
                        {
                            "width": 1080,
                            "height": 1080,
                            "definition": "HD",
                            "url": "/31814/0_6_844831_HD.m3u8",
                            "format": "m3u8",
                            "desc": "超清",
                            "encryptionType": 1,
                            "plaintext": "FNIUpIdbQpc4EzzGnS9DVz/FBOidUkGG60aWf2qrS48=",
                            "rand": "xtEzou0LWvSsH5ObgH9bh0ap5xsY6Xxp5cGH95skhrY=",
                            "encrypt": 1,
                            "duration": "1028.8464",
                            "rate": "637.877",
                            "randInit": "tF2nB3CHWHJjNGaN"
                        }
                    ]
                },
                {
                    "id": "844830",
                    "name": "建立项目XR环境(下)",
                    "courseId": "31814",
                    "url": "/31814/0_7_844830_HD.m3u8",
                    "urls": [
                        {
                            "width": 540,
                            "height": 540,
                            "definition": "LD",
                            "url": "/31814/0_7_844830_LD.m3u8",
                            "format": "m3u8",
                            "desc": "标清",
                            "encryptionType": 1,
                            "plaintext": "n8bmpoEzzei6iDGuABkdEom8cwsEKGNdh3wR/xKmO7s=",
                            "rand": "Np1UK0r0v2KtTqR1ir4OOjgvG97IemS96yeAf8Gzvu4=",
                            "encrypt": 1,
                            "duration": "581.1265",
                            "rate": "339.017",
                            "randInit": "6ePZ5nJx35Kwh0KS"
                        },
                        {
                            "width": 720,
                            "height": 720,
                            "definition": "SD",
                            "url": "/31814/0_7_844830_SD.m3u8",
                            "format": "m3u8",
                            "desc": "高清",
                            "encryptionType": 1,
                            "plaintext": "TepUBthy0Q1gyOl9rXbrUqsnReEvEsrpupTA+iCSsR4=",
                            "rand": "PYnafckfCFh/TAFf9g/6di+bcvUagS9RomsiPJMOlu4=",
                            "encrypt": 1,
                            "duration": "581.1265",
                            "rate": "500.547",
                            "randInit": "6ePZ5nJx35Kwh0KS"
                        },
                        {
                            "width": 1080,
                            "height": 1080,
                            "definition": "HD",
                            "url": "/31814/0_7_844830_HD.m3u8",
                            "format": "m3u8",
                            "desc": "超清",
                            "encryptionType": 1,
                            "plaintext": "LTPsM1CRRxRc8FLI1lWUvWPzY1yLbwScPdkxBZBUcgg=",
                            "rand": "fqnfAvVdBRCID2FHPmpmpOOcDMZB0Yk6OPWL1vwB9SQ=",
                            "encrypt": 1,
                            "duration": "581.1265",
                            "rate": "567.749",
                            "randInit": "6ePZ5nJx35Kwh0KS"
                        }
                    ]
                },
                {
                    "id": "844829",
                    "name": "调试与构建应用(上)",
                    "courseId": "31814",
                    "url": "/31814/0_8_844829_HD.m3u8",
                    "urls": [
                        {
                            "width": 540,
                            "height": 540,
                            "definition": "LD",
                            "url": "/31814/0_8_844829_LD.m3u8",
                            "format": "m3u8",
                            "desc": "标清",
                            "encryptionType": 1,
                            "plaintext": "Ki1EjTgFM5KGZ3/M0+WFG6BUmVnGYah4UDg2UgyRJKw=",
                            "rand": "yaqCBsO1bPQFZHrSm+TmrFLys8/FWLw5S3uJZEGIP80=",
                            "encrypt": 1,
                            "duration": "751.8140",
                            "rate": "362.539",
                            "randInit": "XNS5nYm8SAfAZ8JZ"
                        },
                        {
                            "width": 720,
                            "height": 720,
                            "definition": "SD",
                            "url": "/31814/0_8_844829_SD.m3u8",
                            "format": "m3u8",
                            "desc": "高清",
                            "encryptionType": 1,
                            "plaintext": "K120AmAqw02B7Zhvz3Kw4ieUtp5os0l16LIz/i3Svy4=",
                            "rand": "AWYfHl7+8GHnUsqKzPHldTLRjHzT87zt2izmCptozqo=",
                            "encrypt": 1,
                            "duration": "751.8140",
                            "rate": "540.289",
                            "randInit": "XNS5nYm8SAfAZ8JZ"
                        },
                        {
                            "width": 1080,
                            "height": 1080,
                            "definition": "HD",
                            "url": "/31814/0_8_844829_HD.m3u8",
                            "format": "m3u8",
                            "desc": "超清",
                            "encryptionType": 1,
                            "plaintext": "Wk9cbotUTxo+1R+VZt6n0YRhT0clkLfZHBhMdYSSqDs=",
                            "rand": "GgiDk5fe7YvR4j+OBs/s/LoEv540j4FpAluaQ54ICaA=",
                            "encrypt": 1,
                            "duration": "751.8140",
                            "rate": "677.075",
                            "randInit": "XNS5nYm8SAfAZ8JZ"
                        }
                    ]
                },
                {
                    "id": "844828",
                    "name": "调试与构建应用(下)",
                    "courseId": "31814",
                    "url": "/31814/0_9_844828_HD.m3u8",
                    "urls": [
                        {
                            "width": 540,
                            "height": 540,
                            "definition": "LD",
                            "url": "/31814/0_9_844828_LD.m3u8",
                            "format": "m3u8",
                            "desc": "标清",
                            "encryptionType": 1,
                            "plaintext": "V1SW30DCfs5LOzMgzMmv0tUm0Vi163uD6UMK1MH5B40=",
                            "rand": "nN8x8ufb1ZaqN72iHWKL3BxRVYvQtuxFreRUf/FjorA=",
                            "encrypt": 1,
                            "duration": "291.3169",
                            "rate": "405.421",
                            "randInit": "TnnbDfP2ZnwFieHp"
                        },
                        {
                            "width": 720,
                            "height": 720,
                            "definition": "SD",
                            "url": "/31814/0_9_844828_SD.m3u8",
                            "format": "m3u8",
                            "desc": "高清",
                            "encryptionType": 1,
                            "plaintext": "CiFl6e4nHlb0zrH/AFBgqHv7Lw/8eGBSNyZiyjslzEI=",
                            "rand": "6wNmkf+Ns3H8dAhuub4xBZZQYWYPBwFb71KcR2/9vds=",
                            "encrypt": 1,
                            "duration": "291.3169",
                            "rate": "608.901",
                            "randInit": "TnnbDfP2ZnwFieHp"
                        },
                        {
                            "width": 1080,
                            "height": 1080,
                            "definition": "HD",
                            "url": "/31814/0_9_844828_HD.m3u8",
                            "format": "m3u8",
                            "desc": "超清",
                            "encryptionType": 1,
                            "plaintext": "V6QYBuT3X7L4ca4nTB9NbbtiKxLElktHHtqBwAIJpIo=",
                            "rand": "m7qH8bXfrGnm1dtB2OlxE5EpOOBhwZKOp9ZWyfjQLR4=",
                            "encrypt": 1,
                            "duration": "291.3169",
                            "rate": "787.145",
                            "randInit": "TnnbDfP2ZnwFieHp"
                        }
                    ]
                }
            ]
        },
        {
            "id": "106186",
            "name": "PicoNeo3核心开发技巧",
            "courseId": "31814",
            "sections": [
                {
                    "id": "844827",
                    "name": "地面传送",
                    "courseId": "31814",
                    "url": "/31814/1_0_844827_HD.m3u8",
                    "urls": [
                        {
                            "width": 540,
                            "height": 540,
                            "definition": "LD",
                            "url": "/31814/1_0_844827_LD.m3u8",
                            "format": "m3u8",
                            "desc": "标清",
                            "encryptionType": 1,
                            "plaintext": "M61QaUd3nTLJV6SCtruf0N9/VUAbo0hP+zD2++pce0k=",
                            "rand": "qahpKIa+47AnVtjZdRDrfJfDBpa3RsRvmpKr+NtYWOI=",
                            "encrypt": 1,
                            "duration": "704.2828",
                            "rate": "454.177",
                            "randInit": "7F2pRiCc29bWPJ0r"
                        },
                        {
                            "width": 720,
                            "height": 720,
                            "definition": "SD",
                            "url": "/31814/1_0_844827_SD.m3u8",
                            "format": "m3u8",
                            "desc": "高清",
                            "encryptionType": 1,
                            "plaintext": "b7xVOwoiI1j3xRNEt0AwssY9NBCZ42dGV/CF5S1GxvQ=",
                            "rand": "Yi5bBjLZj8Hbb82Hrhoi3WYKMGYNzZmoFZTySmIcOrY=",
                            "encrypt": 1,
                            "duration": "704.2465",
                            "rate": "695.42",
                            "randInit": "7F2pRiCc29bWPJ0r"
                        },
                        {
                            "width": 1080,
                            "height": 1080,
                            "definition": "HD",
                            "url": "/31814/1_0_844827_HD.m3u8",
                            "format": "m3u8",
                            "desc": "超清",
                            "encryptionType": 1,
                            "plaintext": "5NMltNtVFIPhq5ixZ38G23umu02Le58O5/SUBC2WRqM=",
                            "rand": "HHRhKOvdi+/WaQ4Hkjc2j4CGXg+Jt2WS7PF2Ly41cbU=",
                            "encrypt": 1,
                            "duration": "704.2465",
                            "rate": "887.292",
                            "randInit": "7F2pRiCc29bWPJ0r"
                        }
                    ]
                },
                {
                    "id": "844826",
                    "name": "配置文件更改按键",
                    "courseId": "31814",
                    "url": "/31814/1_1_844826_HD.m3u8",
                    "urls": [
                        {
                            "width": 540,
                            "height": 540,
                            "definition": "LD",
                            "url": "/31814/1_1_844826_LD.m3u8",
                            "format": "m3u8",
                            "desc": "标清",
                            "encryptionType": 1,
                            "plaintext": "wv4lSmr50bc9rM4yV4I2uRlZKApxhqkkfhHnfr+/2sw=",
                            "rand": "SNqzfJ6UgcUt51n1S45cYAY2NTtinK0ezMkYxwqYhz0=",
                            "encrypt": 1,
                            "duration": "688.4465",
                            "rate": "435.435",
                            "randInit": "xQ6arPkAP3mK5yRN"
                        },
                        {
                            "width": 720,
                            "height": 720,
                            "definition": "SD",
                            "url": "/31814/1_1_844826_SD.m3u8",
                            "format": "m3u8",
                            "desc": "高清",
                            "encryptionType": 1,
                            "plaintext": "Q59PPGS6vvN9uSEMhnm2H2BcZvdZxEAIRHD/0bzc9fM=",
                            "rand": "Ex2PLAya0TOXAAVaVGUyCkm1dQWwIrvmB7+7Qc56zoY=",
                            "encrypt": 1,
                            "duration": "688.4468",
                            "rate": "665.601",
                            "randInit": "xQ6arPkAP3mK5yRN"
                        },
                        {
                            "width": 1080,
                            "height": 1080,
                            "definition": "HD",
                            "url": "/31814/1_1_844826_HD.m3u8",
                            "format": "m3u8",
                            "desc": "超清",
                            "encryptionType": 1,
                            "plaintext": "fJflAfwjw9ivSC4NuM4t8Cx28Ffz5qp7Qk3WLCluoUY=",
                            "rand": "Mx5JtCIOCARm/Qw99ytScVQH6gaM/kDPYbesVv7vYRk=",
                            "encrypt": 1,
                            "duration": "688.4468",
                            "rate": "845.103",
                            "randInit": "xQ6arPkAP3mK5yRN"
                        }
                    ]
                },
                {
                    "id": "844825",
                    "name": "锚点传送",
                    "courseId": "31814",
                    "url": "/31814/1_2_844825_HD.m3u8",
                    "urls": [
                        {
                            "width": 540,
                            "height": 540,
                            "definition": "LD",
                            "url": "/31814/1_2_844825_LD.m3u8",
                            "format": "m3u8",
                            "desc": "标清",
                            "encryptionType": 1,
                            "plaintext": "QNZeVjPmX/nBzPQSrbIqMr+duV+gpqTTAAEhtIhmCtw=",
                            "rand": "LGe3nyWv2NqbOpDeEqss9kYN73GWVoM2g3F9BYr2JhY=",
                            "encrypt": 1,
                            "duration": "531.8751",
                            "rate": "465.905",
                            "randInit": "hSwEEpRSWExPPjce"
                        },
                        {
                            "width": 720,
                            "height": 720,
                            "definition": "SD",
                            "url": "/31814/1_2_844825_SD.m3u8",
                            "format": "m3u8",
                            "desc": "高清",
                            "encryptionType": 1,
                            "plaintext": "+RMxjMouzdVu29eSFe6EkCqiEK5j1+JAdBvIZrE+t20=",
                            "rand": "BlDN45yIbp0TS1F7ZVSr4nBLQWkku1E9aYJeDfcPdMU=",
                            "encrypt": 1,
                            "duration": "531.8464",
                            "rate": "714.484",
                            "randInit": "hSwEEpRSWExPPjce"
                        },
                        {
                            "width": 1080,
                            "height": 1080,
                            "definition": "HD",
                            "url": "/31814/1_2_844825_HD.m3u8",
                            "format": "m3u8",
                            "desc": "超清",
                            "encryptionType": 1,
                            "plaintext": "JaQT+Q8mFGEAx2bFQ2UtCMA7vVyVXJhzv0nfG5T3roQ=",
                            "rand": "JJVpH0QUAP+PTfyCgBH+ycvkgp3p6ydSKlJyJ94Zkbg=",
                            "encrypt": 1,
                            "duration": "531.8464",
                            "rate": "932.008",
                            "randInit": "hSwEEpRSWExPPjce"
                        }
                    ]
                },
                {
                    "id": "844824",
                    "name": "控制物体移动",
                    "courseId": "31814",
                    "url": "/31814/1_3_844824_HD.m3u8",
                    "urls": [
                        {
                            "width": 540,
                            "height": 540,
                            "definition": "LD",
                            "url": "/31814/1_3_844824_LD.m3u8",
                            "format": "m3u8",
                            "desc": "标清",
                            "encryptionType": 1,
                            "plaintext": "341G7qyR2QLnZ+3GWZCz7Chk4aaBuom9e+ZjCC+b23E=",
                            "rand": "Rmw6AIWhf1JGcrVXW1PCgUiYe2pPRdMQSM7k/fx/Lh4=",
                            "encrypt": 1,
                            "duration": "736.0464",
                            "rate": "356.065",
                            "randInit": "arcFXa06WGznGt3d"
                        },
                        {
                            "width": 720,
                            "height": 720,
                            "definition": "SD",
                            "url": "/31814/1_3_844824_SD.m3u8",
                            "format": "m3u8",
                            "desc": "高清",
                            "encryptionType": 1,
                            "plaintext": "YRVVy9D6O36HbNIvoqonvisYzKQdbNElsDvPjnVOiN4=",
                            "rand": "XtOYuchm2Be5RmsZCwfxrwQNhRuuqIUIF1x3YgHrrsY=",
                            "encrypt": 1,
                            "duration": "736.0464",
                            "rate": "525.059",
                            "randInit": "arcFXa06WGznGt3d"
                        },
                        {
                            "width": 1080,
                            "height": 1080,
                            "definition": "HD",
                            "url": "/31814/1_3_844824_HD.m3u8",
                            "format": "m3u8",
                            "desc": "超清",
                            "encryptionType": 1,
                            "plaintext": "kI2M7/uCMRetM0C+9nndZvTZWeSLXZMwi/xJgSwbXWQ=",
                            "rand": "TJXZH7uc7PzvONB9k48QSPQpjrtQOoPUeehJawTePOo=",
                            "encrypt": 1,
                            "duration": "736.0464",
                            "rate": "632.751",
                            "randInit": "arcFXa06WGznGt3d"
                        }
                    ]
                },
                {
                    "id": "844823",
                    "name": "Pico调试物体与自身的移动",
                    "courseId": "31814",
                    "url": "/31814/1_4_844823_HD.m3u8",
                    "urls": [
                        {
                            "width": 540,
                            "height": 540,
                            "definition": "LD",
                            "url": "/31814/1_4_844823_LD.m3u8",
                            "format": "m3u8",
                            "desc": "标清",
                            "encryptionType": 1,
                            "plaintext": "1uNkkfoD33uf4pCsVp61ltkddakeGglYVCwmOlNUwJY=",
                            "rand": "4dAruxrda9BS9a90/IKpTwXl59UVZ+x+Hn5iD2jYm0E=",
                            "encrypt": 1,
                            "duration": "580.5264",
                            "rate": "449.788",
                            "randInit": "AFMbhe4tSBxz6NCh"
                        },
                        {
                            "width": 720,
                            "height": 720,
                            "definition": "SD",
                            "url": "/31814/1_4_844823_SD.m3u8",
                            "format": "m3u8",
                            "desc": "高清",
                            "encryptionType": 1,
                            "plaintext": "RvO6PJKucmJ3wglLoBqT+ujBwyDifsGXfb4tHqoRmcQ=",
                            "rand": "Rj+fmQ7Z+HZG7OneLbBOu2DUJQzJN8QbJfVffM3sQqo=",
                            "encrypt": 1,
                            "duration": "580.5439",
                            "rate": "689.233",
                            "randInit": "AFMbhe4tSBxz6NCh"
                        },
                        {
                            "width": 1080,
                            "height": 1080,
                            "definition": "HD",
                            "url": "/31814/1_4_844823_HD.m3u8",
                            "format": "m3u8",
                            "desc": "超清",
                            "encryptionType": 1,
                            "plaintext": "MF0O5pweLw0qxpQC/5SWrusMeTG48IC0j99YovxDIw8=",
                            "rand": "ebkIGZ0wyU+1hkKIsKf/RfdgqPjjXtIHtCjqhi3MbN0=",
                            "encrypt": 1,
                            "duration": "580.5439",
                            "rate": "893.922",
                            "randInit": "AFMbhe4tSBxz6NCh"
                        }
                    ]
                },
                {
                    "id": "844822",
                    "name": "定义手柄按键API",
                    "courseId": "31814",
                    "url": "/31814/1_5_844822_HD.m3u8",
                    "urls": [
                        {
                            "width": 540,
                            "height": 540,
                            "definition": "LD",
                            "url": "/31814/1_5_844822_LD.m3u8",
                            "format": "m3u8",
                            "desc": "标清",
                            "encryptionType": 1,
                            "plaintext": "0GDADoWkRUBswKqgmg3TebyNndrHbwIhEkX99tFIGh8=",
                            "rand": "cnaJc5WnsR8x4YyKgz3wKs9uPaJU9BoM4r1AHZsAcM4=",
                            "encrypt": 1,
                            "duration": "798.7413",
                            "rate": "404.006",
                            "randInit": "bKxjxB4y5GSECkD9"
                        },
                        {
                            "width": 720,
                            "height": 720,
                            "definition": "SD",
                            "url": "/31814/1_5_844822_SD.m3u8",
                            "format": "m3u8",
                            "desc": "高清",
                            "encryptionType": 1,
                            "plaintext": "qDc4e3xrW7KO3cvbPXlBX4rfL6Uq4mk6AEzbdyddrkM=",
                            "rand": "y+DBcWWQmeWCF3/gkYMW8UQLr/bJFNsb2bCsKtBhVFY=",
                            "encrypt": 1,
                            "duration": "798.7646",
                            "rate": "614.729",
                            "randInit": "bKxjxB4y5GSECkD9"
                        },
                        {
                            "width": 1080,
                            "height": 1080,
                            "definition": "HD",
                            "url": "/31814/1_5_844822_HD.m3u8",
                            "format": "m3u8",
                            "desc": "超清",
                            "encryptionType": 1,
                            "plaintext": "EEmX/ozS1S7wFYNC/BCa+239qRb4+t/AOf+I1Fp+Tvk=",
                            "rand": "3bOJ8yZXsyOUWC+tVc34JzwleYWnCKzft+l2IgdXLac=",
                            "encrypt": 1,
                            "duration": "798.7646",
                            "rate": "773.477",
                            "randInit": "bKxjxB4y5GSECkD9"
                        }
                    ]
                },
                {
                    "id": "844821",
                    "name": "测试手柄按键API",
                    "courseId": "31814",
                    "url": "/31814/1_6_844821_HD.m3u8",
                    "urls": [
                        {
                            "width": 540,
                            "height": 540,
                            "definition": "LD",
                            "url": "/31814/1_6_844821_LD.m3u8",
                            "format": "m3u8",
                            "desc": "标清",
                            "encryptionType": 1,
                            "plaintext": "0m2PgNtFbYgaBlyngM2OQRg6dSzaz4Z/CSC9WR3Zjfk=",
                            "rand": "LwbVIfXyXw5yZbhDx7jx0iKeoGiAUMeLJu4SbyYPtWE=",
                            "encrypt": 1,
                            "duration": "888.8464",
                            "rate": "460.193",
                            "randInit": "th0fRJGpAZmkGmR6"
                        },
                        {
                            "width": 720,
                            "height": 720,
                            "definition": "SD",
                            "url": "/31814/1_6_844821_SD.m3u8",
                            "format": "m3u8",
                            "desc": "高清",
                            "encryptionType": 1,
                            "plaintext": "b3HKr8BZY13MpR+NGV4PylAkKcy+/wlRQPft2JNbZ7A=",
                            "rand": "BDf97xaJN4HNS/w26VdQQKgKPjNTh7SOsr9kjyYCFp0=",
                            "encrypt": 1,
                            "duration": "888.8464",
                            "rate": "704.272",
                            "randInit": "th0fRJGpAZmkGmR6"
                        },
                        {
                            "width": 1080,
                            "height": 1080,
                            "definition": "HD",
                            "url": "/31814/1_6_844821_HD.m3u8",
                            "format": "m3u8",
                            "desc": "超清",
                            "encryptionType": 1,
                            "plaintext": "3rZdiK9osGOrgrHhxukz48kb7kqi62grfcYJ0+NfSJ8=",
                            "rand": "o//QrM8l4Am5TPEmcosNq3bbeW1bgBFpv2YfVoGJcx4=",
                            "encrypt": 1,
                            "duration": "888.8464",
                            "rate": "917.045",
                            "randInit": "th0fRJGpAZmkGmR6"
                        }
                    ]
                },
                {
                    "id": "844820",
                    "name": "VR版UI界面",
                    "courseId": "31814",
                    "url": "/31814/1_7_844820_HD.m3u8",
                    "urls": [
                        {
                            "width": 540,
                            "height": 540,
                            "definition": "LD",
                            "url": "/31814/1_7_844820_LD.m3u8",
                            "format": "m3u8",
                            "desc": "标清",
                            "encryptionType": 1,
                            "plaintext": "4woRM1MVa43TuMTKwGZqHQrics1JqOIzDh6YyDq3VLM=",
                            "rand": "9Jk5gGS+qmOBit8Gk2+octE8Kn4v1wlwlbrGOGo1f8M=",
                            "encrypt": 1,
                            "duration": "969.1265",
                            "rate": "451.719",
                            "randInit": "bdRmeaFeZ2BcPQCA"
                        },
                        {
                            "width": 720,
                            "height": 720,
                            "definition": "SD",
                            "url": "/31814/1_7_844820_SD.m3u8",
                            "format": "m3u8",
                            "desc": "高清",
                            "encryptionType": 1,
                            "plaintext": "1zYsU6RSejof102siauTZrq4ijOzx3STSUslaNv1/qw=",
                            "rand": "EkG06k6scd6hivZWxPC+tfuY6XA3pwJcjMEtn+1cmyE=",
                            "encrypt": 1,
                            "duration": "969.1265",
                            "rate": "680.205",
                            "randInit": "bdRmeaFeZ2BcPQCA"
                        },
                        {
                            "width": 1080,
                            "height": 1080,
                            "definition": "HD",
                            "url": "/31814/1_7_844820_HD.m3u8",
                            "format": "m3u8",
                            "desc": "超清",
                            "encryptionType": 1,
                            "plaintext": "fo5fofjRImmIX4pi2ywbKzZOq+NGWJs3XZfdLrK+56Y=",
                            "rand": "ivlhlUOVV+12mDObDBXSrOztSciiT0HTaHr4cwlRbZU=",
                            "encrypt": 1,
                            "duration": "969.1265",
                            "rate": "867.412",
                            "randInit": "bdRmeaFeZ2BcPQCA"
                        }
                    ]
                },
                {
                    "id": "844819",
                    "name": "定义射线回调函数",
                    "courseId": "31814",
                    "url": "/31814/1_8_844819_HD.m3u8",
                    "urls": [
                        {
                            "width": 540,
                            "height": 540,
                            "definition": "LD",
                            "url": "/31814/1_8_844819_LD.m3u8",
                            "format": "m3u8",
                            "desc": "标清",
                            "encryptionType": 1,
                            "plaintext": "5G1UGkUBSCB0WX5DXVm+Yw3nrAcHHjYrmCy40Xd0tiU=",
                            "rand": "coXYC0IeCwhCHqF1qk1z2KfppgYzMvLCoTgVd+5uo2Y=",
                            "encrypt": 1,
                            "duration": "863.8464",
                            "rate": "399.543",
                            "randInit": "JRGsa8SCbQkAakGX"
                        },
                        {
                            "width": 720,
                            "height": 720,
                            "definition": "SD",
                            "url": "/31814/1_8_844819_SD.m3u8",
                            "format": "m3u8",
                            "desc": "高清",
                            "encryptionType": 1,
                            "plaintext": "pM8XlVbJM3J0Qe0yBatCVifmfre1iXVMoAAC4QiP6o8=",
                            "rand": "B6YM/C3HBeQ07uMMX57z3LZXF70NK/+ouGY1iw9VLMk=",
                            "encrypt": 1,
                            "duration": "863.8464",
                            "rate": "601.243",
                            "randInit": "JRGsa8SCbQkAakGX"
                        },
                        {
                            "width": 1080,
                            "height": 1080,
                            "definition": "HD",
                            "url": "/31814/1_8_844819_HD.m3u8",
                            "format": "m3u8",
                            "desc": "超清",
                            "encryptionType": 1,
                            "plaintext": "9mx6dsaAk7DXYW/qyivR5PretldeTLtirI3WW4uWpxc=",
                            "rand": "zlNvdt4HLoG0lJIIx0Wx+nwnM6/meDoO3ubec6Y1aHw=",
                            "encrypt": 1,
                            "duration": "863.8464",
                            "rate": "746.537",
                            "randInit": "JRGsa8SCbQkAakGX"
                        }
                    ]
                },
                {
                    "id": "844818",
                    "name": "调试射线回调函数",
                    "courseId": "31814",
                    "url": "/31814/1_9_844818_HD.m3u8",
                    "urls": [
                        {
                            "width": 540,
                            "height": 540,
                            "definition": "LD",
                            "url": "/31814/1_9_844818_LD.m3u8",
                            "format": "m3u8",
                            "desc": "标清",
                            "encryptionType": 1,
                            "plaintext": "gTgQfetK3jOUVYKQ61LecYV186Qho5jPLaSjkedKZNU=",
                            "rand": "9Uk3n6ty7IRoNiUAlGjCEexPzFW3/+pPfdFLHXeL1Sg=",
                            "encrypt": 1,
                            "duration": "660.0065",
                            "rate": "450.457",
                            "randInit": "yXBBNJY2tbwfGy9M"
                        },
                        {
                            "width": 720,
                            "height": 720,
                            "definition": "SD",
                            "url": "/31814/1_9_844818_SD.m3u8",
                            "format": "m3u8",
                            "desc": "高清",
                            "encryptionType": 1,
                            "plaintext": "8sPJAMTeVIFNeVnTZ0e1ubd7Up8Mg+1xv7Q1fShHN7k=",
                            "rand": "l1Dls4zxH6IXbc2KngBnuBdl+F8Fmwxoa6kqvOPhXD0=",
                            "encrypt": 1,
                            "duration": "660.0065",
                            "rate": "684.504",
                            "randInit": "yXBBNJY2tbwfGy9M"
                        },
                        {
                            "width": 1080,
                            "height": 1080,
                            "definition": "HD",
                            "url": "/31814/1_9_844818_HD.m3u8",
                            "format": "m3u8",
                            "desc": "超清",
                            "encryptionType": 1,
                            "plaintext": "iXw7PP38+bTB2EMfJQPu4dc52OIbjmyRt24mzj7mRCk=",
                            "rand": "MY+U9g9hs2axvtJZmHfih9qZv2iC6QU6X/YUH/sFk2k=",
                            "encrypt": 1,
                            "duration": "660.0065",
                            "rate": "886.524",
                            "randInit": "yXBBNJY2tbwfGy9M"
                        }
                    ]
                },
                {
                    "id": "844817",
                    "name": "SDK版本API异同分析",
                    "courseId": "31814",
                    "url": "/31814/1_10_844817_HD.m3u8",
                    "urls": [
                        {
                            "width": 540,
                            "height": 540,
                            "definition": "LD",
                            "url": "/31814/1_10_844817_LD.m3u8",
                            "format": "m3u8",
                            "desc": "标清",
                            "encryptionType": 1,
                            "plaintext": "7aOsUresUeTxYOa2XXrxF5DA1YLcKi63v5k6Bs3x6sU=",
                            "rand": "XDRzdhvsiPWY8nGtyv4hAS+jJIL87z5U5Du4YqAM/78=",
                            "encrypt": 1,
                            "duration": "559.4835",
                            "rate": "354.064",
                            "randInit": "FMsnTGnxMxjXAjBe"
                        },
                        {
                            "width": 720,
                            "height": 720,
                            "definition": "SD",
                            "url": "/31814/1_10_844817_SD.m3u8",
                            "format": "m3u8",
                            "desc": "高清",
                            "encryptionType": 1,
                            "plaintext": "OPMPs79IQj7MjwY8RCzraJ9CzwK0t+CESzryojRZ1pc=",
                            "rand": "LglSbD18mOcmoiOXTrNXCHaHk2zKgaVhPtzOe8OQDMU=",
                            "encrypt": 1,
                            "duration": "559.4465",
                            "rate": "532.647",
                            "randInit": "FMsnTGnxMxjXAjBe"
                        },
                        {
                            "width": 1080,
                            "height": 1080,
                            "definition": "HD",
                            "url": "/31814/1_10_844817_HD.m3u8",
                            "format": "m3u8",
                            "desc": "超清",
                            "encryptionType": 1,
                            "plaintext": "QjPk2CHYuZr8/QKPKFf6Xwm2KBgusNj7/m7gk3Lzl8M=",
                            "rand": "ZYr6ougzYlEiOl2VtzMQYDaLu5kj2ARj13lw3rUOWT4=",
                            "encrypt": 1,
                            "duration": "559.4465",
                            "rate": "641.649",
                            "randInit": "FMsnTGnxMxjXAjBe"
                        }
                    ]
                }
            ]
        },
        {
            "id": "106187",
            "name": "PicoNeo3基础综合案例",
            "courseId": "31814",
            "sections": [
                {
                    "id": "844816",
                    "name": "综合案例_场景搭建",
                    "courseId": "31814",
                    "url": "/31814/2_0_844816_HD.m3u8",
                    "urls": [
                        {
                            "width": 540,
                            "height": 540,
                            "definition": "LD",
                            "url": "/31814/2_0_844816_LD.m3u8",
                            "format": "m3u8",
                            "desc": "标清",
                            "encryptionType": 1,
                            "plaintext": "8EQWRuz6/UDWjkeZ7Nn9uuOsHia1eijgnQAXlF5jwIQ=",
                            "rand": "of0afCE1aO1+Vp7pXWSjVf16nxL3TaPEVD6oWLHTnpU=",
                            "encrypt": 1,
                            "duration": "888.5264",
                            "rate": "401.583",
                            "randInit": "b67wbn5nHmeDiTMN"
                        },
                        {
                            "width": 720,
                            "height": 720,
                            "definition": "SD",
                            "url": "/31814/2_0_844816_SD.m3u8",
                            "format": "m3u8",
                            "desc": "高清",
                            "encryptionType": 1,
                            "plaintext": "hMkky8qa41eI18wkmMtTHIkT++QJW1XTcpWq1jPU9qI=",
                            "rand": "W9HAUlQHWsZm8LJkJQv97NKkqnVzZu+lXy5GoeRtC7E=",
                            "encrypt": 1,
                            "duration": "888.5264",
                            "rate": "595.43",
                            "randInit": "b67wbn5nHmeDiTMN"
                        },
                        {
                            "width": 1080,
                            "height": 1080,
                            "definition": "HD",
                            "url": "/31814/2_0_844816_HD.m3u8",
                            "format": "m3u8",
                            "desc": "超清",
                            "encryptionType": 1,
                            "plaintext": "DI9elfT58YeIptIRs8Zdvrb8jfPbi+6Fh9TPmsRA3lI=",
                            "rand": "W3E77PKl70Cm1SzZ/0DCRReUtUjap1X+YyM0vKBVXok=",
                            "encrypt": 1,
                            "duration": "888.5264",
                            "rate": "746.163",
                            "randInit": "b67wbn5nHmeDiTMN"
                        }
                    ]
                },
                {
                    "id": "844815",
                    "name": "伸缩杆测试",
                    "courseId": "31814",
                    "url": "/31814/2_1_844815_HD.m3u8",
                    "urls": [
                        {
                            "width": 540,
                            "height": 540,
                            "definition": "LD",
                            "url": "/31814/2_1_844815_LD.m3u8",
                            "format": "m3u8",
                            "desc": "标清",
                            "encryptionType": 1,
                            "plaintext": "cJYj2/HiQxI0gxvhorO58EeVi6bY8qbNVjnekv77Cz4=",
                            "rand": "hSAR19499WEmefufPr0KP4wrEXLlyqNLgqwXLoCWFwA=",
                            "encrypt": 1,
                            "duration": "903.4631",
                            "rate": "374.991",
                            "randInit": "nMzjAXPiW5462nxt"
                        },
                        {
                            "width": 720,
                            "height": 720,
                            "definition": "SD",
                            "url": "/31814/2_1_844815_SD.m3u8",
                            "format": "m3u8",
                            "desc": "高清",
                            "encryptionType": 1,
                            "plaintext": "7u1QfCUn08Zmlgv85KKieCNLraAZXfslC3izutkzJmQ=",
                            "rand": "ngS6Yn5QxFw7skQEchPLfJn1w3vVIZm4kdcaadXSY4Y=",
                            "encrypt": 1,
                            "duration": "903.4465",
                            "rate": "561.235",
                            "randInit": "nMzjAXPiW5462nxt"
                        },
                        {
                            "width": 1080,
                            "height": 1080,
                            "definition": "HD",
                            "url": "/31814/2_1_844815_HD.m3u8",
                            "format": "m3u8",
                            "desc": "超清",
                            "encryptionType": 1,
                            "plaintext": "PRsMxHp+UjRVXgil7MKiLryvJneP1r6rejP4XeHGaDs=",
                            "rand": "kirbaSbfH0OxTba8pLfUVe3YV6dyqMadw7HjzXzk7NM=",
                            "encrypt": 1,
                            "duration": "903.4465",
                            "rate": "684.491",
                            "randInit": "nMzjAXPiW5462nxt"
                        }
                    ]
                },
                {
                    "id": "844814",
                    "name": "锚点单向伸缩",
                    "courseId": "31814",
                    "url": "/31814/2_2_844814_HD.m3u8",
                    "urls": [
                        {
                            "width": 540,
                            "height": 540,
                            "definition": "LD",
                            "url": "/31814/2_2_844814_LD.m3u8",
                            "format": "m3u8",
                            "desc": "标清",
                            "encryptionType": 1,
                            "plaintext": "AjmGxn9dscWGvOaIdyylUOmKg2eNxwk8zqb1hMuk2tc=",
                            "rand": "WJn0zGH2uk4tVW0W9LO/VvnAo1+hsS3e8y31KosIC80=",
                            "encrypt": 1,
                            "duration": "515.1335",
                            "rate": "394.407",
                            "randInit": "t79eeBEjbmHDcJ2r"
                        },
                        {
                            "width": 720,
                            "height": 720,
                            "definition": "SD",
                            "url": "/31814/2_2_844814_SD.m3u8",
                            "format": "m3u8",
                            "desc": "高清",
                            "encryptionType": 1,
                            "plaintext": "BAkg08MLyG9Pbj3FuxMfl5bKjWjN7tldLYVRkaMe+t4=",
                            "rand": "tc+v/LPENXhz11E3Db3v5IRmgFkqp0/iZL6F1VeD11I=",
                            "encrypt": 1,
                            "duration": "515.1567",
                            "rate": "587.347",
                            "randInit": "t79eeBEjbmHDcJ2r"
                        },
                        {
                            "width": 1080,
                            "height": 1080,
                            "definition": "HD",
                            "url": "/31814/2_2_844814_HD.m3u8",
                            "format": "m3u8",
                            "desc": "超清",
                            "encryptionType": 1,
                            "plaintext": "j6VA29S1bWe/H47Ce0u1ZZJ4mrqkxCVllb7OczRj6cw=",
                            "rand": "pD8jznZw3ZEDvylnoQ1MQFCbgjVUTDV2VJY753HPBzA=",
                            "encrypt": 1,
                            "duration": "515.1567",
                            "rate": "716.325",
                            "randInit": "t79eeBEjbmHDcJ2r"
                        }
                    ]
                },
                {
                    "id": "844813",
                    "name": "模型触发检测脚本",
                    "courseId": "31814",
                    "url": "/31814/2_3_844813_HD.m3u8",
                    "urls": [
                        {
                            "width": 540,
                            "height": 540,
                            "definition": "LD",
                            "url": "/31814/2_3_844813_LD.m3u8",
                            "format": "m3u8",
                            "desc": "标清",
                            "encryptionType": 1,
                            "plaintext": "kNeCxMrRy0pEeABrk9BFLW6KVebhGMSYcrv0hugor7E=",
                            "rand": "fQRqSDk2qKHFFUQBpM7Xue2QoI1TpV1LBtqa6LSs3wI=",
                            "encrypt": 1,
                            "duration": "993.5563",
                            "rate": "393.872",
                            "randInit": "MfbWzEyr9Ksib9GM"
                        },
                        {
                            "width": 720,
                            "height": 720,
                            "definition": "SD",
                            "url": "/31814/2_3_844813_SD.m3u8",
                            "format": "m3u8",
                            "desc": "高清",
                            "encryptionType": 1,
                            "plaintext": "FilrUBhf0Z4foXSb9VAupWawtgoQE7NdVxHQ5OyC7Cw=",
                            "rand": "aEbu2nw1OWyeciILFOHkAJMgrNrrjTI5T9d2w1PVD+c=",
                            "encrypt": 1,
                            "duration": "993.5563",
                            "rate": "576.426",
                            "randInit": "MfbWzEyr9Ksib9GM"
                        },
                        {
                            "width": 1080,
                            "height": 1080,
                            "definition": "HD",
                            "url": "/31814/2_3_844813_HD.m3u8",
                            "format": "m3u8",
                            "desc": "超清",
                            "encryptionType": 1,
                            "plaintext": "rBwhDjHbVT75DeJ3o2RiaQOGVG6C7S82HPKsN20HIKM=",
                            "rand": "OUuQYZ/5JVirb3Z/K9U9BfOeM8q/OpyL0ob6ZiUPulI=",
                            "encrypt": 1,
                            "duration": "993.5563",
                            "rate": "724.476",
                            "randInit": "MfbWzEyr9Ksib9GM"
                        }
                    ]
                },
                {
                    "id": "844812",
                    "name": "定义机械爪控制脚本",
                    "courseId": "31814",
                    "url": "/31814/2_4_844812_HD.m3u8",
                    "urls": [
                        {
                            "width": 540,
                            "height": 540,
                            "definition": "LD",
                            "url": "/31814/2_4_844812_LD.m3u8",
                            "format": "m3u8",
                            "desc": "标清",
                            "encryptionType": 1,
                            "plaintext": "hy0jlULp6OgT+ubQo7AWANzZajgEehzdTSpeNSy5PZ8=",
                            "rand": "w9nSI510/EIT3Lmu6Y2ExKS8QUL3/IsPsISBUba+wHU=",
                            "encrypt": 1,
                            "duration": "953.9664",
                            "rate": "403.075",
                            "randInit": "pEiYaNHADCjkE3jf"
                        },
                        {
                            "width": 720,
                            "height": 720,
                            "definition": "SD",
                            "url": "/31814/2_4_844812_SD.m3u8",
                            "format": "m3u8",
                            "desc": "高清",
                            "encryptionType": 1,
                            "plaintext": "HrYMe+i6DODb9VfILhmjL4PkB/rEBkFcMA/r09MsjdQ=",
                            "rand": "plybDQ85zKftMYv/YEw14In6P+ElSBT/oOVHiUhNAb8=",
                            "encrypt": 1,
                            "duration": "953.9432",
                            "rate": "594.832",
                            "randInit": "pEiYaNHADCjkE3jf"
                        },
                        {
                            "width": 1080,
                            "height": 1080,
                            "definition": "HD",
                            "url": "/31814/2_4_844812_HD.m3u8",
                            "format": "m3u8",
                            "desc": "超清",
                            "encryptionType": 1,
                            "plaintext": "Yo6PNjkZDNmdaH7C5v0Haq8DdXko7STmm7B5vm6xrQg=",
                            "rand": "K1U+yMliLIadsia5RQd2F58A/kwObXr3JEGwPHUQ9ZA=",
                            "encrypt": 1,
                            "duration": "953.9432",
                            "rate": "748.711",
                            "randInit": "pEiYaNHADCjkE3jf"
                        }
                    ]
                },
                {
                    "id": "844811",
                    "name": "完善机械爪控制脚本",
                    "courseId": "31814",
                    "url": "/31814/2_5_844811_HD.m3u8",
                    "urls": [
                        {
                            "width": 540,
                            "height": 540,
                            "definition": "LD",
                            "url": "/31814/2_5_844811_LD.m3u8",
                            "format": "m3u8",
                            "desc": "标清",
                            "encryptionType": 1,
                            "plaintext": "03bLQwpiHXRX7+/IRWk6S+s48HhXPSNT+0W/nTcaR9Q=",
                            "rand": "8tMD28VhYwptwujV82eC9jRg8A5B0qEbFng+JY+hVZc=",
                            "encrypt": 1,
                            "duration": "868.3264",
                            "rate": "417.54",
                            "randInit": "xDeYtfEZRX2AE3MP"
                        },
                        {
                            "width": 720,
                            "height": 720,
                            "definition": "SD",
                            "url": "/31814/2_5_844811_SD.m3u8",
                            "format": "m3u8",
                            "desc": "高清",
                            "encryptionType": 1,
                            "plaintext": "Tok5TirjT/XeLg4UkyKjFGgV2zTLrbPUYVjbw6ZhelI=",
                            "rand": "Y550vRE8SUXydJpRFcFuNUZM2bKIYKakiI+zmhBMCJM=",
                            "encrypt": 1,
                            "duration": "868.3264",
                            "rate": "612.531",
                            "randInit": "xDeYtfEZRX2AE3MP"
                        },
                        {
                            "width": 1080,
                            "height": 1080,
                            "definition": "HD",
                            "url": "/31814/2_5_844811_HD.m3u8",
                            "format": "m3u8",
                            "desc": "超清",
                            "encryptionType": 1,
                            "plaintext": "beQC/Si2kUfRVRCMdJmx3Xe7K8i0Fqziidxgsjhsnx0=",
                            "rand": "TKz1R24hfjbFpnG98hjOb9zz/CraeC8muHSFfEzj8GY=",
                            "encrypt": 1,
                            "duration": "868.3264",
                            "rate": "790.422",
                            "randInit": "xDeYtfEZRX2AE3MP"
                        }
                    ]
                },
                {
                    "id": "844810",
                    "name": "VR环境调试与改进",
                    "courseId": "31814",
                    "url": "/31814/2_6_844810_HD.m3u8",
                    "urls": [
                        {
                            "width": 540,
                            "height": 540,
                            "definition": "LD",
                            "url": "/31814/2_6_844810_LD.m3u8",
                            "format": "m3u8",
                            "desc": "标清",
                            "encryptionType": 1,
                            "plaintext": "YOn5Ajm1i4WABcwW4KgoSqVG5J5OEnFbLpk97a1MAu8=",
                            "rand": "WB9R3HH9qJngXvPqCzmVI7cRNvrusuCPfRBkWNR30ok=",
                            "encrypt": 1,
                            "duration": "801.7264",
                            "rate": "444.474",
                            "randInit": "2JmPk6SQiNwse6C3"
                        },
                        {
                            "width": 720,
                            "height": 720,
                            "definition": "SD",
                            "url": "/31814/2_6_844810_SD.m3u8",
                            "format": "m3u8",
                            "desc": "高清",
                            "encryptionType": 1,
                            "plaintext": "Mj/uGnxKh7S0iFCVxbX3RaAm1Lk1FcNtrTDLuNbj7gM=",
                            "rand": "T35bRahLOam5ck3ulRbcuYcNBha8cEpzWnr27R2CTk8=",
                            "encrypt": 1,
                            "duration": "801.7264",
                            "rate": "677.835",
                            "randInit": "2JmPk6SQiNwse6C3"
                        },
                        {
                            "width": 1080,
                            "height": 1080,
                            "definition": "HD",
                            "url": "/31814/2_6_844810_HD.m3u8",
                            "format": "m3u8",
                            "desc": "超清",
                            "encryptionType": 1,
                            "plaintext": "bv+p3EUjHsXMBAV6RYZf6ThVtnTyeEkSbbXG6IsAujg=",
                            "rand": "3qoj0vTSvicym2jw8fuuZiwoLBwRGK0h5H0mY/Mq0hY=",
                            "encrypt": 1,
                            "duration": "801.7264",
                            "rate": "880.472",
                            "randInit": "2JmPk6SQiNwse6C3"
                        }
                    ]
                },
                {
                    "id": "844809",
                    "name": "VR增加UI界面统计",
                    "courseId": "31814",
                    "url": "/31814/2_7_844809_HD.m3u8",
                    "urls": [
                        {
                            "width": 540,
                            "height": 540,
                            "definition": "LD",
                            "url": "/31814/2_7_844809_LD.m3u8",
                            "format": "m3u8",
                            "desc": "标清",
                            "encryptionType": 1,
                            "plaintext": "f3NwWoNDjqG1u3wsX378Rrd1pNwyhPmYseqHw0ufINs=",
                            "rand": "hNGiDYkcsrk6Oo7GJ6+mJncp05CSSmggxp6fo4e5Iu0=",
                            "encrypt": 1,
                            "duration": "905.4465",
                            "rate": "385.457",
                            "randInit": "HtTPYRTZy8R5Qjc9"
                        },
                        {
                            "width": 720,
                            "height": 720,
                            "definition": "SD",
                            "url": "/31814/2_7_844809_SD.m3u8",
                            "format": "m3u8",
                            "desc": "高清",
                            "encryptionType": 1,
                            "plaintext": "P8jJUyFc6krZKUI2DwyMdR/qETWEeMB60vPR5Lm0hVM=",
                            "rand": "9du9gZ1zHkK8SCPTh5XWtbSSgkfy8GyX2olkmJhxtmM=",
                            "encrypt": 1,
                            "duration": "905.4465",
                            "rate": "571.148",
                            "randInit": "HtTPYRTZy8R5Qjc9"
                        },
                        {
                            "width": 1080,
                            "height": 1080,
                            "definition": "HD",
                            "url": "/31814/2_7_844809_HD.m3u8",
                            "format": "m3u8",
                            "desc": "超清",
                            "encryptionType": 1,
                            "plaintext": "Hs6Go1GFak1YHRFvPxJuzwZpAg2fKrw9ZRfUzrtM76I=",
                            "rand": "y8Wv/T+QQm1rwPOwTnpgvuiMMsWGXFn8HlJBqi4QQhM=",
                            "encrypt": 1,
                            "duration": "905.4465",
                            "rate": "694.475",
                            "randInit": "HtTPYRTZy8R5Qjc9"
                        }
                    ]
                },
                {
                    "id": "844808",
                    "name": "综合案例_VR调试完毕(课程结束)",
                    "courseId": "31814",
                    "url": "/31814/2_8_844808_HD.m3u8",
                    "urls": [
                        {
                            "width": 540,
                            "height": 540,
                            "definition": "LD",
                            "url": "/31814/2_8_844808_LD.m3u8",
                            "format": "m3u8",
                            "desc": "标清",
                            "encryptionType": 1,
                            "plaintext": "pSueI56DzVsdlE2dca1/+X/o1qU+dYjDLywHpAUFSJ0=",
                            "rand": "3/yLd0eLUZiLuYQRIJlH+MQkPQ6w+Gln6PVuOVBKAmw=",
                            "encrypt": 1,
                            "duration": "406.6966",
                            "rate": "410.724",
                            "randInit": "aiPCKmamp0xR4Qa2"
                        },
                        {
                            "width": 720,
                            "height": 720,
                            "definition": "SD",
                            "url": "/31814/2_8_844808_SD.m3u8",
                            "format": "m3u8",
                            "desc": "高清",
                            "encryptionType": 1,
                            "plaintext": "BI+NoUEr75Gps/9+DKevzRi4a6AqtEwZVGdCpNKIH98=",
                            "rand": "oJnpWug4stebSRU5OcO+hFmHE2paKTj+bhHw/achEi8=",
                            "encrypt": 1,
                            "duration": "406.6864",
                            "rate": "617.707",
                            "randInit": "aiPCKmamp0xR4Qa2"
                        },
                        {
                            "width": 1080,
                            "height": 1080,
                            "definition": "HD",
                            "url": "/31814/2_8_844808_HD.m3u8",
                            "format": "m3u8",
                            "desc": "超清",
                            "encryptionType": 1,
                            "plaintext": "UCNs8DXNd4RXZkgmsmCUr2hPYmiVmr6cTCmZC440cM0=",
                            "rand": "Mur+/oI/gqdW4NtrjhGiDrQCQxt7qIFU2U9aNbyat/A=",
                            "encrypt": 1,
                            "duration": "406.6864",
                            "rate": "788.781",
                            "randInit": "aiPCKmamp0xR4Qa2"
                        }
                    ]
                }
            ]
        }
    ]
}